[{"url":"https://live.staticflickr.com/65535/52719891475_08c402c800_z.jpg","desc":"fresh prince of","user":"by Desolate Places","link":"https://www.flickr.com/photos/neversaydie/"},{"url":"https://live.staticflickr.com/7052/6800574024_d8e94365c2_w.jpg","desc":"Lasa - Cyprus","user":"by ATHOS THEOCHARIDES On and Off","link":"https://www.flickr.com/photos/77237839@N03/"},{"url":"https://live.staticflickr.com/65535/52719443452_886806705b.jpg","desc":"cantina 07 silos","user":"by Massimo Baldo","link":"https://www.flickr.com/photos/mb89/"},{"url":"https://live.staticflickr.com/65535/52720429343_13582ddc3e_w.jpg","desc":"Château de Haut-Bois","user":"by Ted Potters","link":"https://www.flickr.com/photos/149271704@N02/"},{"url":"https://live.staticflickr.com/65535/52720401499_a8c035b48c_z.jpg","desc":"_1090055_DxO","user":"by Matthew Davis","link":"https://www.flickr.com/photos/196105790@N03/"},{"url":"https://live.staticflickr.com/65535/52720134131_4ef2997fd0_w.jpg","desc":"Abandoned Trolley","user":"by Michael Coghlan","link":"https://www.flickr.com/photos/mikecogh/"},{"url":"https://live.staticflickr.com/65535/52719757287_4eecf33bd5_w.jpg","desc":"A true story. (on explore with many thanks March 3, 2023)","user":"by Faye Rigopoulou","link":"https://www.flickr.com/photos/fayerigopoulou/"},{"url":"https://live.staticflickr.com/65535/52592187026_d481c2401a_z.jpg","desc":"Be'er Sheva - Abandoned","user":"by Miklos Palko","link":"https://www.flickr.com/photos/photomp-nl/"},{"url":"https://live.staticflickr.com/65535/52720175180_bb13a3e4bb.jpg","desc":"Palace Hotel","user":"by Berny Sackl","link":"https://www.flickr.com/photos/192959875@N05/"},{"url":"https://live.staticflickr.com/65535/52720766187_e96f80e5d5_w.jpg","desc":"Meghraj Resort, Sajek","user":"by shishir fajsal","link":"https://www.flickr.com/photos/shishir_fajsal/"},{"url":"https://live.staticflickr.com/65535/52721405161_07c7296340_w.jpg","desc":"Sortir du lot","user":"by Lyvie","link":"https://www.flickr.com/photos/185963757@N03/"},{"url":"https://live.staticflickr.com/65535/52721942258_9c1740c341_w.jpg","desc":"the little morgue","user":"by Gentleman-of-Decay","link":"https://www.flickr.com/photos/164756855@N05/"},{"url":"https://live.staticflickr.com/65535/52721954318_03f7b10f9c_z.jpg","desc":"Abandoned","user":"by Alice Sartori","link":"https://www.flickr.com/photos/187140657@N04/"},{"url":"https://live.staticflickr.com/65535/51089595090_d9b92eae1d.jpg","desc":"Wisteria Magic","user":"by Lynda Christison","link":"https://www.flickr.com/photos/184337559@N06/"},{"url":"https://live.staticflickr.com/65535/51999231616_0034e09c1f_c.jpg","desc":"The cages","user":"by Carmen Claudia Mihai","link":"https://www.flickr.com/photos/183609841@N03/"},{"url":"https://live.staticflickr.com/65535/52721492112_5b655d2a21_c.jpg","desc":"What Beacon?","user":"by Graham  Innes","link":"https://www.flickr.com/photos/183190746@N05/"},{"url":"https://live.staticflickr.com/65535/52722816665_968cd932de_w.jpg","desc":"101_1103","user":"by Nicole Sprute","link":"https://www.flickr.com/photos/197140465@N02/"},{"url":"https://live.staticflickr.com/65535/52717221453_f1243329d4.jpg","desc":"","user":"by Urbex by ČÁSTY","link":"https://www.flickr.com/photos/197124247@N05/"},{"url":"https://live.staticflickr.com/65535/52723247983_b2b6d18499_w.jpg","desc":"Former factory","user":"by Cristiano Antognotti","link":"https://www.flickr.com/photos/capo69/"},{"url":"https://live.staticflickr.com/65535/52722883506_3134867dc0_w.jpg","desc":"la poudrerie-04581","user":"by Under The Dust","link":"https://www.flickr.com/photos/154808163@N02/"},{"url":"https://live.staticflickr.com/65535/52723530975_7166259d9f_w.jpg","desc":"Fujidanacho#4","user":"by tetsuo matsumoto","link":"https://www.flickr.com/photos/19432592@N08/"},{"url":"https://live.staticflickr.com/65535/52723480059_61b6e82f62_w.jpg","desc":"time is a jet plane","user":"by Desolate Places","link":"https://www.flickr.com/photos/neversaydie/"},{"url":"https://live.staticflickr.com/65535/52723661290_9287478183_w.jpg","desc":"Maboroshi-Hakurankai, Ito, Shizuoka Pref.","user":"by Kento Nagatsuka","link":"https://www.flickr.com/photos/197823465@N08/"},{"url":"https://live.staticflickr.com/65535/52723521476_bd253e62eb_w.jpg","desc":"Mur de soutien","user":"by Lyvie","link":"https://www.flickr.com/photos/185963757@N03/"},{"url":"https://live.staticflickr.com/65535/52723102812_3c2a08be88_w.jpg","desc":"\"Birds of a feather,\" or perhaps \"Feathers of a bird,\" would be more appropriate.","user":"by Dances With Cobwebs","link":"https://www.flickr.com/photos/192663928@N06/"},{"url":"https://live.staticflickr.com/65535/51672941297_85d923f56b_w.jpg","desc":"243A7498.jpg","user":"by Karsten Bretschneider","link":"https://www.flickr.com/photos/karstenbretschneider/"},{"url":"https://live.staticflickr.com/65535/51707939831_8c8f30d615_w.jpg","desc":"Béziers","user":"by Daniel Mielniczek Photography","link":"https://www.flickr.com/photos/danielmielniczekphotography/"},{"url":"https://live.staticflickr.com/65535/52724715609_717928ddca_n.jpg","desc":"Old age in a car and van spare parts dealership, please clean me!","user":"by spelio","link":"https://www.flickr.com/photos/spelio/"},{"url":"https://live.staticflickr.com/65535/52724076252_b2d9470e90.jpg","desc":"overview","user":"by Gentleman-of-Decay","link":"https://www.flickr.com/photos/164756855@N05/"},{"url":"https://live.staticflickr.com/65535/52725116168_9487d225ed_w.jpg","desc":"Il profumo della solitudine","user":"by Cristiano Antognotti","link":"https://www.flickr.com/photos/capo69/"},{"url":"https://live.staticflickr.com/65535/52725003054_a446b134ac_w.jpg","desc":"Viet Cong.","user":"by Dust Brothers Inside","link":"https://www.flickr.com/photos/81514330@N03/"},{"url":"https://live.staticflickr.com/65535/52725330110_a1d32052af_w.jpg","desc":"Traumhafter Arbeitsplatz","user":"by piloba_imagines","link":"https://www.flickr.com/photos/piloba/"},{"url":"https://live.staticflickr.com/1974/44887855112_4d5ecd01a9_w.jpg","desc":"Vergessene Welten","user":"by Jens Bretschneider","link":"https://www.flickr.com/photos/127825117@N08/"},{"url":"https://live.staticflickr.com/65535/52722248832_39c714e898.jpg","desc":"Palace Hotel","user":"by Berny Sackl","link":"https://www.flickr.com/photos/192959875@N05/"},{"url":"https://live.staticflickr.com/65535/52724630609_1fb28a1310_w.jpg","desc":"IMG_6972.jpg","user":"by Jack Gray","link":"https://www.flickr.com/photos/jackgray0000/"},{"url":"https://live.staticflickr.com/65535/52724778625_45ebae4f67_w.jpg","desc":"The Wagon Shed","user":"by Tm Elmer","link":"https://www.flickr.com/photos/64903145@N04/"},{"url":"https://live.staticflickr.com/65535/52723098127_6d6e5554a6.jpg","desc":"Rural decay","user":"by John Carrel","link":"https://www.flickr.com/photos/46355638@N00/"},{"url":"https://live.staticflickr.com/65535/52723992463_a7a7144975_w.jpg","desc":"Vicoletti","user":"by Pasquale Tassone","link":"https://www.flickr.com/photos/138939439@N06/"},{"url":"https://live.staticflickr.com/65535/51162187878_beae7b10d2_w.jpg","desc":"Parinacota","user":"by Christophe Chelé","link":"https://www.flickr.com/photos/christophe-chele/"},{"url":"https://live.staticflickr.com/65535/52722163250_c2d3156f5f_w.jpg","desc":"Palace Hotel - pool 2","user":"by Berny Sackl","link":"https://www.flickr.com/photos/192959875@N05/"},{"url":"https://live.staticflickr.com/65535/52723235883_7bd876c5a1_w.jpg","desc":"365-2023-061","user":"by CharClarPhoto","link":"https://www.flickr.com/photos/charclarphoto/"},{"url":"https://live.staticflickr.com/65535/52722454253_3954d75309_w.jpg","desc":"Ghost Signs","user":"by Jay","link":"https://www.flickr.com/photos/lionel682/"},{"url":"https://live.staticflickr.com/5836/31220807436_691acede4e.jpg","desc":"Fotospaziergang II","user":"by Grüner Nomade","link":"https://www.flickr.com/photos/gruenernomade/"},{"url":"https://live.staticflickr.com/65535/52719122887_51601be429_w.jpg","desc":"Escaping from Escapism","user":"by Maximos Halbert","link":"https://www.flickr.com/photos/halbertmax/"},{"url":"https://live.staticflickr.com/65535/52720703705_3d75f73ae7.jpg","desc":"Old and abandoned","user":"by Melnee Benfield","link":"https://www.flickr.com/photos/mbbenfield/"},{"url":"https://live.staticflickr.com/65535/52718248873_e73a467576_w.jpg","desc":"Game of lines","user":"by Travelling Slonik","link":"https://www.flickr.com/photos/190022557@N04/"},{"url":"https://live.staticflickr.com/65535/52721174240_715c878ffb_z.jpg","desc":"Un ristretto pubblico di intellettuali","user":"by Cristiano Antognotti","link":"https://www.flickr.com/photos/capo69/"},{"url":"https://live.staticflickr.com/65535/52360758892_552fb03fcb_w.jpg","desc":"The last layer","user":"by Rainer Jehde","link":"https://www.flickr.com/photos/183499175@N08/"},{"url":"https://live.staticflickr.com/4918/45714217681_1382eb0e7d_z.jpg","desc":"KS002041_MontePalace","user":"by KS_aus_F","link":"https://www.flickr.com/photos/ks_aus_f/"},{"url":"https://live.staticflickr.com/65535/52597940524_8af5065d7b_n.jpg","desc":"Stairway for nowhere","user":"by Ejipehel","link":"https://www.flickr.com/photos/ejipehel/"}]