[{"url":"https://live.staticflickr.com/65535/51580109829_d6663de71c.jpg","desc":"Andalucía-432","user":"by Fotgrafo-robby25","link":"https://www.flickr.com/photos/robby25/"},{"url":"https://live.staticflickr.com/8153/28823092741_bc64bcf04b_c.jpg","desc":"Voigtlander Nokton 35mm/F1.2  ASPH II","user":"by Ryan Chang","link":"https://www.flickr.com/photos/126193098@N07/"},{"url":"https://live.staticflickr.com/65535/51577188578_b4a9d13c3a.jpg","desc":"Rain a Coming","user":"by Peter Stabolepszy","link":"https://www.flickr.com/photos/peakinpete/"},{"url":"https://live.staticflickr.com/65535/51580202760_7698ecc6b6_w.jpg","desc":"Twilight Zone roses","user":"by Ingrid Van Streepen","link":"https://www.flickr.com/photos/87959883@N02/"},{"url":"https://live.staticflickr.com/65535/51580182920_aa15b2a5a1_w.jpg","desc":"-","user":"by txmx 2","link":"https://www.flickr.com/photos/txmx-2/"},{"url":"https://live.staticflickr.com/65535/51579089110_734b491371.jpg","desc":"Flatcloud","user":"by Jon Arne Foss","link":"https://www.flickr.com/photos/92647872@N05/"},{"url":"https://live.staticflickr.com/65535/51578374577_f3012dfeb3_c.jpg","desc":"Toblerone","user":"by Teh Han Lin","link":"https://www.flickr.com/photos/vibranze/"},{"url":"https://live.staticflickr.com/65535/51573919386_878908b115_c.jpg","desc":"SEAWEED","user":"by Sofia Fateeva","link":"https://www.flickr.com/photos/193313363@N06/"},{"url":"https://live.staticflickr.com/5830/20987840068_9d45047a04_z.jpg","desc":"Coloured balls #3","user":"by Jerome  Rondeau","link":"https://www.flickr.com/photos/jrrondeau/"},{"url":"https://live.staticflickr.com/65535/51578299272_97101b029c_w.jpg","desc":"","user":"by Stonepicker+","link":"https://www.flickr.com/photos/stonepicker/"},{"url":"https://live.staticflickr.com/65535/51579015231_1c45afb8aa_w.jpg","desc":"2021-10-12_04-43-10","user":"by Costel Photography","link":"https://www.flickr.com/photos/39771770@N03/"},{"url":"https://live.staticflickr.com/65535/51578130567_fa52a6fb09_w.jpg","desc":"Oleander","user":"by Kab Cheol Jeong","link":"https://www.flickr.com/photos/jeongkabcheol/"},{"url":"https://live.staticflickr.com/65535/51578923541_c11e27109e_w.jpg","desc":"KP__9913","user":"by Serge C","link":"https://www.flickr.com/photos/163071155@N03/"},{"url":"https://live.staticflickr.com/65535/51579551269_518984ae77_w.jpg","desc":"Hoover Dam","user":"by david albright","link":"https://www.flickr.com/photos/193688997@N07/"},{"url":"https://live.staticflickr.com/65535/51509374956_db9be5fd66_w.jpg","desc":"P9160097MZ75300EXT10SCG","user":"by hyphy2008","link":"https://www.flickr.com/photos/hyphy2008/"},{"url":"https://live.staticflickr.com/65535/51579732975_f048d15cbc.jpg","desc":"bee on borage - crop","user":"by Nick","link":"https://www.flickr.com/photos/nickant44/"},{"url":"https://live.staticflickr.com/897/40185677355_9168f33a8f_w.jpg","desc":"Casa de Hacienda","user":"by Oscar Padilla Álvarez","link":"https://www.flickr.com/photos/137216627@N04/"},{"url":"https://live.staticflickr.com/65535/51579023073_57c6207af3.jpg","desc":"DSC07791-2","user":"by GheeBeeGhee","link":"https://www.flickr.com/photos/116003582@N04/"},{"url":"https://live.staticflickr.com/65535/51229822036_b8d98b677d_w.jpg","desc":"Pink Daisies","user":"by w guy b","link":"https://www.flickr.com/photos/wguyb/"},{"url":"https://live.staticflickr.com/65535/51577865397_4775f847cd.jpg","desc":"Vermont","user":"by Jackie Touw Photography","link":"https://www.flickr.com/photos/jackietouw/"},{"url":"https://live.staticflickr.com/65535/51574888067_2e57486909_c.jpg","desc":"R0000693","user":"by Greg Baikaloff","link":"https://www.flickr.com/photos/156948960@N05/"},{"url":"https://live.staticflickr.com/65535/51495025992_1a7c304127_c.jpg","desc":"Red Rock Canyon Pano","user":"by Matt Heitzman","link":"https://www.flickr.com/photos/193958210@N05/"},{"url":"https://live.staticflickr.com/65535/51578563791_d8c533ee75_c.jpg","desc":"BAYAS","user":"by JesúsFRM","link":"https://www.flickr.com/photos/jesuspzn/"},{"url":"https://live.staticflickr.com/4851/45772136262_7a6b8ce7ce.jpg","desc":"Alone In The Dark...","user":"by lillypotpie","link":"https://www.flickr.com/photos/lillian_fisher/"},{"url":"https://live.staticflickr.com/65535/51417995398_472578cabe_w.jpg","desc":"There Are Too Many Mediocre Things In Life; Love Shouldn't Be One Of Them","user":"by Natasa Opacic","link":"https://www.flickr.com/photos/101390044@N08/"},{"url":"https://live.staticflickr.com/3852/15158940015_64f78f44e9_w.jpg","desc":"Jewel Box flowers 33","user":"by Tim Richards","link":"https://www.flickr.com/photos/pentaxpastor/"},{"url":"https://live.staticflickr.com/65535/51578369791_42242456e3_w.jpg","desc":"Weltmädchentag 2021 - Bochum","user":"by divertom68","link":"https://www.flickr.com/photos/divertom68/"},{"url":"https://live.staticflickr.com/65535/51577552722_d51d9de6eb_z.jpg","desc":"Final Fall Flower","user":"by Joshua Hiltbrand","link":"https://www.flickr.com/photos/190652504@N06/"},{"url":"https://live.staticflickr.com/1617/25622916725_9fa0d7314c_w.jpg","desc":"Cardiff Castle","user":"by Graham Willetts","link":"https://www.flickr.com/photos/majorgjw/"},{"url":"https://live.staticflickr.com/65535/51577480088_e5e795be51_w.jpg","desc":"Yellow Trio","user":"by wotanseyepatch","link":"https://www.flickr.com/photos/wotanseyepatch/"},{"url":"https://live.staticflickr.com/65535/51578277961_b60a7c08f2_z.jpg","desc":"Autumn Leaves","user":"by Regine Fahlbusch","link":"https://www.flickr.com/photos/169070938@N03/"},{"url":"https://live.staticflickr.com/65535/51578249771_5fc58ba78c_c.jpg","desc":"Atlanta Airport Jungle","user":"by moonjazz","link":"https://www.flickr.com/photos/moonjazz/"},{"url":"https://live.staticflickr.com/65535/51578817074_b48342cfc3_z.jpg","desc":"1997 Corvette GT1","user":"by David G. Schultz","link":"https://www.flickr.com/photos/dschultz742/"},{"url":"https://live.staticflickr.com/65535/51578363048_12b04c15d5_n.jpg","desc":"Yellow-orange Fly Agaric Mushroom","user":"by swmartz","link":"https://www.flickr.com/photos/swmpix64/"},{"url":"https://live.staticflickr.com/65535/51574288794_efabd2f7d3_w.jpg","desc":"","user":"by mokastet","link":"https://www.flickr.com/photos/mokastet/"},{"url":"https://live.staticflickr.com/65535/51578747129_668d20f05a_w.jpg","desc":"Mountain river 2","user":"by Charles P.","link":"https://www.flickr.com/photos/141133568@N07/"},{"url":"https://live.staticflickr.com/65535/50641768551_10bf1fcede_c.jpg","desc":"Sunset@Ajman","user":"by Gautam Sethi","link":"https://www.flickr.com/photos/182269266@N07/"},{"url":"https://live.staticflickr.com/65535/51569141828_518b9e51f8_c.jpg","desc":"","user":"by Graham S Paton","link":"https://www.flickr.com/photos/graham_paton/"},{"url":"https://live.staticflickr.com/65535/51094553199_085dd03b6e_c.jpg","desc":"Intimate landscape","user":"by Stefan Johansson","link":"https://www.flickr.com/photos/144824822@N06/"},{"url":"https://live.staticflickr.com/65535/51577985771_bd5724d997_w.jpg","desc":"Herfst (autumn)","user":"by Coby","link":"https://www.flickr.com/photos/polletjes/"},{"url":"https://live.staticflickr.com/65535/51576365961_fb328cfc36.jpg","desc":"“give the ones you love wings to fly, roots to come back and reasons to stay”","user":"by Elisa Stefanescu","link":"https://www.flickr.com/photos/153025721@N02/"},{"url":"https://live.staticflickr.com/65535/51578647299_bf2104ce9e_w.jpg","desc":"Ehi…una foto anche a me 📷","user":"by Anna Viscomi","link":"https://www.flickr.com/photos/97019005@N08/"},{"url":"https://live.staticflickr.com/65535/51578828055_cdfc2a078b_w.jpg","desc":"_MC14342-1","user":"by M Coopwood","link":"https://www.flickr.com/photos/153077200@N03/"},{"url":"https://live.staticflickr.com/65535/51578058033_57c47cde36_w.jpg","desc":"Yellow Lines","user":"by Pete","link":"https://www.flickr.com/photos/karnevil/"},{"url":"https://live.staticflickr.com/65535/51578713480_dc8e34346c.jpg","desc":"La catedral de Veracruz. Es una edificación cuyo inicio de construcción data de principios del siglo XVIII. Realizada mayormente en coral y cantera.","user":"by Zarkmex","link":"https://www.flickr.com/photos/193924519@N07/"},{"url":"https://live.staticflickr.com/65535/51539882584_aff4b2d9e1.jpg","desc":"Rope climbing...","user":"by Kostas Kaisidis","link":"https://www.flickr.com/photos/kostaskaisidis/"},{"url":"https://live.staticflickr.com/65535/51576971127_6cb5c23671_w.jpg","desc":"La dernière valse","user":"by marilia barbaud","link":"https://www.flickr.com/photos/133090461@N06/"},{"url":"https://live.staticflickr.com/65535/49673410427_8e4a9361e3_w.jpg","desc":"Girl with a red cloth","user":"by Paul Mühlbach","link":"https://www.flickr.com/photos/dotcher/"},{"url":"https://live.staticflickr.com/65535/51578700885_b85426f0e6_z.jpg","desc":"_DSC2168","user":"by Jarosław Mizera","link":"https://www.flickr.com/photos/142836216@N04/"},{"url":"https://live.staticflickr.com/65535/51576937317_f0659870c7_w.jpg","desc":"21-09-05 DSCF8292 1","user":"by GholaGhola","link":"https://www.flickr.com/photos/duncanidaho/"}]